<?xml version="1.0" encoding="UTF-8"?>

<PropertyList>

  <sim>
    <model>
      <livery>
         <name type="string">USAF 354 TFS - Grim Reaper</name>
     <texture-fuselage>Liveries/354grim/fuselage2.png</texture-fuselage>
     <texture-wing>Liveries/354grim/wings.png</texture-wing>
	 <texture-pylon>Liveries/354grim/pylons.png</texture-pylon>
	  <texture-vtail>Liveries/354grim/vtail.png</texture-vtail>
	 <texture-htail>Liveries/354grim/htail.png</texture-htail>
      <texture-pylon>Liveries/354grim/pylons.png</texture-pylon>
	   <texture-tanks>Liveries/354grimn/tanks.png</texture-tanks>
     <texture-misc>Liveries/354grimn/misc.png</texture-misc>

      </livery>
    </model>
  </sim>

</PropertyList>
